{
    "audio": null,
    "beatsnap": {
      "id": 1738084404760,
      "index": 1,
      "options": [
        "Composition Determined",
        "None",
        "8 Bars",
        "4 Bars",
        "2 Bars",
        "1 Bar",
        "1/2 Bar",
        "1/4 Bar"
      ],
      "value": "None",
      "valuetype": "ParamChoice"
    },
    "colorid": {
      "id": 1738084404793,
      "index": 0,
      "options": [
        "1",
        "2",
        "3",
        "4",
        "5",
        "6"
      ],
      "value": "1",
      "valuetype": "ParamChoice"
    },
    "connected": {
      "id": 1738084404794,
      "index": 4,
      "options": [
        "Empty",
        "Disconnected",
        "Previewing",
        "Connected",
        "Connected \u0026 previewing"
      ],
      "value": "Connected \u0026 previewing",
      "valuetype": "ParamState"
    },
    "dashboard": {
      "Link 1": {
        "id": 1738084404714,
        "in": 0.0,
        "max": 1.0,
        "min": 0.0,
        "out": 1.0,
        "value": 0.0,
        "valuetype": "ParamRange",
        "view": {
          "control_type": "rotary",
          "suffix": ""
        }
      },
      "Link 2": {
        "id": 1738084404715,
        "in": 0.0,
        "max": 1.0,
        "min": 0.0,
        "out": 1.0,
        "value": 0.0,
        "valuetype": "ParamRange",
        "view": {
          "control_type": "rotary",
          "suffix": ""
        }
      },
      "Link 3": {
        "id": 1738084404716,
        "in": 0.0,
        "max": 1.0,
        "min": 0.0,
        "out": 1.0,
        "value": 0.0,
        "valuetype": "ParamRange",
        "view": {
          "control_type": "rotary",
          "suffix": ""
        }
      },
      "Link 4": {
        "id": 1738084404717,
        "in": 0.0,
        "max": 1.0,
        "min": 0.0,
        "out": 1.0,
        "value": 0.0,
        "valuetype": "ParamRange",
        "view": {
          "control_type": "rotary",
          "suffix": ""
        }
      },
      "Link 5": {
        "id": 1738084404718,
        "in": 0.0,
        "max": 1.0,
        "min": 0.0,
        "out": 1.0,
        "value": 0.0,
        "valuetype": "ParamRange",
        "view": {
          "control_type": "rotary",
          "suffix": ""
        }
      },
      "Link 6": {
        "id": 1738084404719,
        "in": 0.0,
        "max": 1.0,
        "min": 0.0,
        "out": 1.0,
        "value": 0.0,
        "valuetype": "ParamRange",
        "view": {
          "control_type": "rotary",
          "suffix": ""
        }
      },
      "Link 7": {
        "id": 1738084404723,
        "in": 0.0,
        "max": 1.0,
        "min": 0.0,
        "out": 1.0,
        "value": 0.0,
        "valuetype": "ParamRange",
        "view": {
          "control_type": "rotary",
          "suffix": ""
        }
      },
      "Link 8": {
        "id": 1738084404727,
        "in": 0.0,
        "max": 1.0,
        "min": 0.0,
        "out": 1.0,
        "value": 0.0,
        "valuetype": "ParamRange",
        "view": {
          "control_type": "rotary",
          "suffix": ""
        }
      }
    },
    "faderstart": {
      "id": 1738084404790,
      "index": 0,
      "options": [
        "Layer Determined",
        "On",
        "Off"
      ],
      "value": "Layer Determined",
      "valuetype": "ParamChoice"
    },
    "id": 1621342719991,
    "ignorecolumntrigger": {
      "id": 1738084404785,
      "index": 0,
      "options": [
        "Layer Determined",
        "On",
        "Off"
      ],
      "value": "Layer Determined",
      "valuetype": "ParamChoice"
    },
    "name": {
      "id": 1738084404792,
      "value": "test",
      "valuetype": "ParamString"
    },
    "selected": {
      "id": 1738084404797,
      "value": true,
      "valuetype": "ParamTrigger"
    },
    "target": {
      "id": 1738084404775,
      "index": 0,
      "options": [
        "Composition Determined",
        "Active Layer",
        "Own Layer",
        "Free Layer",
        "Denon Player Determined",
        "Pioneer Player Determined"
      ],
      "value": "Composition Determined",
      "valuetype": "ParamChoice"
    },
    "thumbnail": {
      "id": 1621342719991,
      "is_default": false,
      "last_update": "1738084407188397",
      "path": "/api/v1/composition/clips/by-id/1621342719991/thumbnail",
      "size": 51188
    },
    "transport": {
      "controls": {
        "duration": {
          "id": 1738084407567,
          "in": 0.001,
          "max": 604800.0,
          "min": 0.001,
          "out": 604800.0,
          "value": 8.0,
          "valuetype": "ParamRange"
        },
        "playdirection": {
          "id": 1738084407544,
          "index": 2,
          "options": [
            "\u003c",
            "||",
            "\u003e"
          ],
          "value": "\u003e",
          "valuetype": "ParamChoice"
        },
        "playmode": {
          "id": 1738084407546,
          "index": 0,
          "options": [
            "Loop",
            "Bounce",
            "Random",
            "Play Once \u0026 Clear",
            "Play Once \u0026 Hold"
          ],
          "value": "Loop",
          "valuetype": "ParamChoice"
        },
        "playmodeaway": {
          "id": 1738084407547,
          "index": 0,
          "options": [
            "Restart",
            "Continue",
            "Relative"
          ],
          "value": "Restart",
          "valuetype": "ParamChoice"
        },
        "speed": {
          "id": 1738084407552,
          "in": 0.0,
          "max": 10.0,
          "min": 0.0,
          "out": 10.0,
          "value": 1.0,
          "valuetype": "ParamRange"
        }
      },
      "position": {
        "id": 1738084407499,
        "in": 0.0,
        "max": 8000.000000000001,
        "min": 0.0,
        "out": 8000.000000000001,
        "value": 2347.5124166606784,
        "valuetype": "ParamRange"
      }
    },
    "transporttype": {
      "id": 1738084404765,
      "index": 0,
      "options": [
        "Timeline",
        "BPM Sync",
        "SMPTE 1",
        "SMPTE 2",
        "Denon DJ",
        "Pioneer DJ"
      ],
      "value": "Timeline",
      "valuetype": "ParamChoice"
    },
    "triggerstyle": {
      "id": 1738084404780,
      "index": 0,
      "options": [
        "Composition Determined",
        "Normal",
        "Piano",
        "Toggle"
      ],
      "value": "Composition Determined",
      "valuetype": "ParamChoice"
    },
    "video": {
      "a": {
        "id": 1738084407029,
        "value": false,
        "valuetype": "ParamBoolean"
      },
      "b": {
        "id": 1738084407028,
        "value": true,
        "valuetype": "ParamBoolean"
      },
      "description": "FogAndDust_3.mov\nDXV 3.0 Normal Quality, No Alpha, 1280x720, 30.00 Fps\n00:00:08.000",
      "effects": [
        {
          "display_name": "Transform",
          "id": 1621342719995,
          "mixer": null,
          "name": "Transform",
          "params": {
            "Anchor X": {
              "id": 1738084407244,
              "in": -8192.0,
              "max": 8192.0,
              "min": -8192.0,
              "out": 8192.0,
              "value": 0.0,
              "valuetype": "ParamRange",
              "view": {
                "control_type": "slider",
                "step": 1.0,
                "suffix": ""
              }
            },
            "Anchor Y": {
              "id": 1738084407253,
              "in": -8192.0,
              "max": 8192.0,
              "min": -8192.0,
              "out": 8192.0,
              "value": 0.0,
              "valuetype": "ParamRange",
              "view": {
                "control_type": "slider",
                "step": 1.0,
                "suffix": ""
              }
            },
            "Anchor Z": {
              "id": 1738084407259,
              "in": -8192.0,
              "max": 8192.0,
              "min": -8192.0,
              "out": 8192.0,
              "value": 0.0,
              "valuetype": "ParamRange",
              "view": {
                "control_type": "slider",
                "step": 1.0,
                "suffix": ""
              }
            },
            "Position X": {
              "id": 1738084407161,
              "in": -16384.0,
              "max": 16384.0,
              "min": -16384.0,
              "out": 16384.0,
              "value": 0.0,
              "valuetype": "ParamRange",
              "view": {
                "control_type": "spinner",
                "display_units": "real",
                "step": 1.0,
                "suffix": ""
              }
            },
            "Position Y": {
              "id": 1738084407203,
              "in": -16384.0,
              "max": 16384.0,
              "min": -16384.0,
              "out": 16384.0,
              "value": 0.0,
              "valuetype": "ParamRange",
              "view": {
                "control_type": "spinner",
                "display_units": "real",
                "step": 1.0,
                "suffix": ""
              }
            },
            "Rotation X": {
              "id": 1738084407218,
              "in": -180.0,
              "max": 180.0,
              "min": -180.0,
              "out": 180.0,
              "value": 0.0,
              "valuetype": "ParamRange",
              "view": {
                "control_type": "slider",
                "display_units": "degrees",
                "step": 1.0,
                "suffix": " \u00b0"
              }
            },
            "Rotation Y": {
              "id": 1738084407231,
              "in": -180.0,
              "max": 180.0,
              "min": -180.0,
              "out": 180.0,
              "value": 0.0,
              "valuetype": "ParamRange",
              "view": {
                "control_type": "slider",
                "display_units": "degrees",
                "step": 1.0,
                "suffix": " \u00b0"
              }
            },
            "Rotation Z": {
              "id": 1738084407241,
              "in": -180.0,
              "max": 180.0,
              "min": -180.0,
              "out": 180.0,
              "value": 0.0,
              "valuetype": "ParamRange",
              "view": {
                "control_type": "slider",
                "display_units": "degrees",
                "step": 1.0,
                "suffix": " \u00b0"
              }
            },
            "Scale": {
              "id": 1738084407137,
              "in": 0.0,
              "max": 1000.0,
              "min": 0.0,
              "out": 1000.0,
              "value": 100.0,
              "valuetype": "ParamRange",
              "view": {
                "control_type": "slider",
                "display_units": "percent",
                "multiplier": 1.0,
                "step": 1.0,
                "suffix": " %"
              }
            },
            "Scale H": {
              "id": 1738084407147,
              "in": 0.0,
              "max": 1000.0,
              "min": 0.0,
              "out": 1000.0,
              "value": 100.0,
              "valuetype": "ParamRange",
              "view": {
                "control_type": "slider",
                "display_units": "percent",
                "multiplier": 1.0,
                "step": 1.0,
                "suffix": " %"
              }
            },
            "Scale W": {
              "id": 1738084407139,
              "in": 0.0,
              "max": 1000.0,
              "min": 0.0,
              "out": 1000.0,
              "value": 100.0,
              "valuetype": "ParamRange",
              "view": {
                "control_type": "slider",
                "display_units": "percent",
                "multiplier": 1.0,
                "step": 1.0,
                "suffix": " %"
              }
            }
          }
        }
      ],
      "fileinfo": {
        "duration": "00:00:08.00",
        "duration_ms": 8000.000000000001,
        "exists": true,
        "framerate": {
          "denom": 1,
          "num": 30
        },
        "height": 720,
        "path": "/Applications/Resolume Arena/media/Shop74/FogAndDust_3.mov",
        "width": 1280
      },
      "g": {
        "id": 1738084407026,
        "value": true,
        "valuetype": "ParamBoolean"
      },
      "height": {
        "id": 1738084406997,
        "in": 0.0,
        "max": 16384.0,
        "min": 0.0,
        "out": 16384.0,
        "value": 1080.0,
        "valuetype": "ParamRange"
      },
      "mixer": null,
      "opacity": {
        "id": 1738084406995,
        "in": 0.0,
        "max": 1.0,
        "min": 0.0,
        "out": 1.0,
        "value": 1.0,
        "valuetype": "ParamRange"
      },
      "r": {
        "id": 1738084407025,
        "value": true,
        "valuetype": "ParamBoolean"
      },
      "resize": {
        "id": 1738084407023,
        "index": 3,
        "options": [
          "Fill",
          "Fit",
          "Stretch",
          "Original"
        ],
        "value": "Original",
        "valuetype": "ParamChoice"
      },
      "sourceparams": null,
      "width": {
        "id": 1738084406996,
        "in": 0.0,
        "max": 16384.0,
        "min": 0.0,
        "out": 16384.0,
        "value": 1920.0,
        "valuetype": "ParamRange"
      }
    }
  }